fun_utilities_and_games/__init__.py
fun_utilities_and_games/basic_calculator.py
fun_utilities_and_games/bmi_calculator.py
fun_utilities_and_games/currency_converter.py
fun_utilities_and_games/digital_clock.py
fun_utilities_and_games/hangman.py
fun_utilities_and_games/number_guesser.py
fun_utilities_and_games/palindrome_checker.py
fun_utilities_and_games/password_generator.py
fun_utilities_and_games/riddle_game.py
fun_utilities_and_games/rock_paper_scissor.py
fun_utilities_and_games/snake_game.py
fun_utilities_and_games/student_form.py
fun_utilities_and_games/temperature_converter.py
fun_utilities_and_games/tic_tac_toe.py
fun_utilities_and_games/word_scrambler.py
fun_utilities_and_games/wordle_game.py
fun_utilities_and_games-0.1.6.dist-info/LICENSE
fun_utilities_and_games-0.1.6.dist-info/METADATA
fun_utilities_and_games-0.1.6.dist-info/WHEEL
fun_utilities_and_games-0.1.6.dist-info/top_level.txt
fun_utilities_and_games-0.1.6.dist-info/RECORD
